Workbook

Sheet Instrucoes
A1: Gastos Orlando · compartilhados + pessoais (tipo Splitwise)
A3: Site: https://eduardohidekiy.github.io/viagem-orlando/
A4: Membros: Eduardo, Karina, Bruno, Gabriele
A6: O QUE LANÇAR AQUI
A7: TUDO que você quiser acompanhar na viagem:
A8: • Compartilhado — casa, carro, mercado, Uber juntos… (divide e gera saldo entre vocês)
A9: • Pessoal — seu ingresso, seu e-SIM, sua lembrancinha, seu almoço sozinho… (entra no SEU total da viagem e NÃO gera dívida)
A11: COMO USAR NO GOOGLE SHEETS
A12: 1. Upload deste arquivo no Drive → Abrir com Planilhas Google → Salvar como Planilhas Google.
A13: 2. Aba Gastos: selecione F2:I121 (Eduardo…Gabriele) → Inserir → Caixa de seleção.
A14: 3. Compartilhar com o grupo (edição).
A15: 4. Cole o link no site (PLANILHA_GASTOS).
... A31: (Nos pessoais, pagou e cota se anulam — o saldo só muda com compartilhados.)

Sheet Membros
A1: Nome | B1: Núcleo | C1: Ativo
A2: Eduardo | B2: Família | C2: TRUE
A3: Karina | B3: Família | C3: TRUE
A4: Bruno | B4: Casal | C4: TRUE
A5: Gabriele | B5: Casal | C5: TRUE
A7: Não renomeie os nomes sem ajustar as fórmulas.

Sheet Gastos
A1: Data | B1: Descrição | C1: Valor (R$) | D1: Quem pagou | E1: Tipo | F1: Eduardo | G1: Karina | H1: Bruno | I1: Gabriele | J1: Cota Eduardo | K1: Cota Karina | L1: Cota Bruno | M1: Cota Gabriele | N1: Qtd pessoas | O1: Categoria | P1: Obs
B2: EXEMPLO compartilh. — Mercado Walmart (apague) | C2: 400 | D2: Bruno | E2: Compartilhado | F2: TRUE | G2: TRUE | H2: TRUE | I2: TRUE | J2: =IF(C2="","",IF(E2="Pessoal",IF(D2="Eduardo",C2,0),IF(N2=0,"",IF(F2=TRUE,C2/N2,0)))) | K2: =IF(C2="","",IF(E2="Pessoal",IF(D2="Karina",C2,0),IF(N2=0,"",IF(G2=TRUE,C2/N2,0)))) | L2: =IF(C2="","",IF(E2="Pessoal",IF(D2="Bruno",C2,0),IF(N2=0,"",IF(H2=TRUE,C2/N2,0)))) | M2: =IF(C2="","",IF(E2="Pessoal",IF(D2="Gabriele",C2,0),IF(N2=0,"",IF(I2=TRUE,C2/N2,0)))) | N2: =IF(C2="","",IF(E2="Pessoal",1,COUNTIF(F2:I2,TRUE))) | O2: Mercado | P2: ÷ 4
B3: EXEMPLO pessoal — e-SIM do Eduardo (apague) | C3: 175 | D3: Eduardo | E3: Pessoal | F3: FALSE | G3: FALSE | H3: FALSE | I3: FALSE | J3: =IF(C3="","",IF(E3="Pessoal",IF(D3="Eduardo",C3,0),IF(N3=0,"",IF(F3=TRUE,C3/N3,0)))) | K3: =IF(C3="","",IF(E3="Pessoal",IF(D3="Karina",C3,0),IF(N3=0,"",IF(G3=TRUE,C3/N3,0)))) | L3: =IF(C3="","",IF(E3="Pessoal",IF(D3="Bruno",C3,0),IF(N3=0,"",IF(H3=TRUE,C3/N3,0)))) | M3: =IF(C3="","",IF(E3="Pessoal",IF(D3="Gabriele",C3,0),IF(N3=0,"",IF(I3=TRUE,C3/N3,0)))) | N3: =IF(C3="","",IF(E3="Pessoal",1,COUNTIF(F3:I3,TRUE))) | O3: Internet | P3: Só entra no custo dele
B4: EXEMPLO pessoal — lembrancinha Karina (apague) | C4: 80 | D4: Karina | E4: Pessoal | F4: FALSE | G4: FALSE | H4: FALSE | I4: FALSE | J4: =IF(C4="","",IF(E4="Pessoal",IF(D4="Eduardo",C4,0),IF(N4=0,"",IF(F4=TRUE,C4/N4,0)))) | K4: =IF(C4="","",IF(E4="Pessoal",IF(D4="Karina",C4,0),IF(N4=0,"",IF(G4=TRUE,C4/N4,0)))) | L4: =IF(C4="","",IF(E4="Pessoal",IF(D4="Bruno",C4,0),IF(N4=0,"",IF(H4=TRUE,C4/N4,0)))) | M4: =IF(C4="","",IF(E4="Pessoal",IF(D4="Gabriele",C4,0),IF(N4=0,"",IF(I4=TRUE,C4/N4,0)))) | N4: =IF(C4="","",IF(E4="Pessoal",1,COUNTIF(F4:I4,TRUE))) | O4: Lembrancinha
F5: FALSE | G5: FALSE | H5: FALSE | I5: FALSE | J5: =IF(C5="","",IF(E5="Pessoal",IF(D5="Eduardo",C5,0),IF(N5=0,"",IF(F5=TRUE,C5/N5,0)))) | K5: =IF(C5="","",IF(E5="Pessoal",IF(D5="Karina",C5,0),IF(N5=0,"",IF(G5=TRUE,C5/N5,0)))) | L5: =IF(C5="","",IF(E5="Pessoal",IF(D5="Bruno",C5,0),IF(N5=0,"",IF(H5=TRUE,C5/N5,0)))) | M5: =IF(C5="","",IF(E5="Pessoal",IF(D5="Gabriele",C5,0),IF(N5=0,"",IF(I5=TRUE,C5/N5,0)))) | N5: =IF(C5="","",IF(E5="Pessoal",1,COUNTIF(F5:I5,TRUE)))
F6: FALSE | G6: FALSE | H6: FALSE | I6: FALSE | J6: =IF(C6="","",IF(E6="Pessoal",IF(D6="Eduardo",C6,0),IF(N6=0,"",IF(F6=TRUE,C6/N6,0)))) | K6: =IF(C6="","",IF(E6="Pessoal",IF(D6="Karina",C6,0),IF(N6=0,"",IF(G6=TRUE,C6/N6,0)))) | L6: =IF(C6="","",IF(E6="Pessoal",IF(D6="Bruno",C6,0),IF(N6=0,"",IF(H6=TRUE,C6/N6,0)))) | M6: =IF(C6="","",IF(E6="Pessoal",IF(D6="Gabriele",C6,0),IF(N6=0,"",IF(I6=TRUE,C6/N6,0)))) | N6: =IF(C6="","",IF(E6="Pessoal",1,COUNTIF(F6:I6,TRUE)))
F7: FALSE | G7: FALSE | H7: FALSE | I7: FALSE | J7: =IF(C7="","",IF(E7="Pessoal",IF(D7="Eduardo",C7,0),IF(N7=0,"",IF(F7=TRUE,C7/N7,0)))) | K7: =IF(C7="","",IF(E7="Pessoal",IF(D7="Karina",C7,0),IF(N7=0,"",IF(G7=TRUE,C7/N7,0)))) | L7: =IF(C7="","",IF(E7="Pessoal",IF(D7="Bruno",C7,0),IF(N7=0,"",IF(H7=TRUE,C7/N7,0)))) | M7: =IF(C7="","",IF(E7="Pessoal",IF(D7="Gabriele",C7,0),IF(N7=0,"",IF(I7=TRUE,C7/N7,0)))) | N7: =IF(C7="","",IF(E7="Pessoal",1,COUNTIF(F7:I7,TRUE)))
F8: FALSE | G8: FALSE | H8: FALSE | I8: FALSE | J8: =IF(C8="","",IF(E8="Pessoal",IF(D8="Eduardo",C8,0),IF(N8=0,"",IF(F8=TRUE,C8/N8,0)))) | K8: =IF(C8="","",IF(E8="Pessoal",IF(D8="Karina",C8,0),IF(N8=0,"",IF(G8=TRUE,C8/N8,0)))) | L8: =IF(C8="","",IF(E8="Pessoal",IF(D8="Bruno",C8,0),IF(N8=0,"",IF(H8=TRUE,C8/N8,0)))) | M8: =IF(C8="","",IF(E8="Pessoal",IF(D8="Gabriele",C8,0),IF(N8=0,"",IF(I8=TRUE,C8/N8,0)))) | N8: =IF(C8="","",IF(E8="Pessoal",1,COUNTIF(F8:I8,TRUE)))
F9: FALSE | G9: FALSE | H9: FALSE | I9: FALSE | J9: =IF(C9="","",IF(E9="Pessoal",IF(D9="Eduardo",C9,0),IF(N9=0,"",IF(F9=TRUE,C9/N9,0)))) | K9: =IF(C9="","",IF(E9="Pessoal",IF(D9="Karina",C9,0),IF(N9=0,"",IF(G9=TRUE,C9/N9,0)))) | L9: =IF(C9="","",IF(E9="Pessoal",IF(D9="Bruno",C9,0),IF(N9=0,"",IF(H9=TRUE,C9/N9,0)))) | M9: =IF(C9="","",IF(E9="Pessoal",IF(D9="Gabriele",C9,0),IF(N9=0,"",IF(I9=TRUE,C9/N9,0)))) | N9: =IF(C9="","",IF(E9="Pessoal",1,COUNTIF(F9:I9,TRUE)))
F10: FALSE | G10: FALSE | H10: FALSE | I10: FALSE | J10: =IF(C10="","",IF(E10="Pessoal",IF(D10="Eduardo",C10,0),IF(N10=0,"",IF(F10=TRUE,C10/N10,0)))) | K10: =IF(C10="","",IF(E10="Pessoal",IF(D10="Karina",C10,0),IF(N10=0,"",IF(G10=TRUE,C10/N10,0)))) | L10: =IF(C10="","",IF(E10="Pessoal",IF(D10="Bruno",C10,0),IF(N10=0,"",IF(H10=TRUE,C10/N10,0)))) | M10: =IF(C10="","",IF(E10="Pessoal",IF(D10="Gabriele",C10,0),IF(N10=0,"",IF(I10=TRUE,C10/N10,0)))) | N10: =IF(C10="","",IF(E10="Pessoal",1,COUNTIF(F10:I10,TRUE)))
F11: FALSE | G11: FALSE | H11: FALSE | I11: FALSE | J11: =IF(C11="","",IF(E11="Pessoal",IF(D11="Eduardo",C11,0),IF(N11=0,"",IF(F11=TRUE,C11/N11,0)))) | K11: =IF(C11="","",IF(E11="Pessoal",IF(D11="Karina",C11,0),IF(N11=0,"",IF(G11=TRUE,C11/N11,0)))) | L11: =IF(C11="","",IF(E11="Pessoal",IF(D11="Bruno",C11,0),IF(N11=0,"",IF(H11=TRUE,C11/N11,0)))) | M11: =IF(C11="","",IF(E11="Pessoal",IF(D11="Gabriele",C11,0),IF(N11=0,"",IF(I11=TRUE,C11/N11,0)))) | N11: =IF(C11="","",IF(E11="Pessoal",1,COUNTIF(F11:I11,TRUE)))
F12: FALSE | G12: FALSE | H12: FALSE | I12: FALSE | J12: =IF(C12="","",IF(E12="Pessoal",IF(D12="Eduardo",C12,0),IF(N12=0,"",IF(F12=TRUE,C12/N12,0)))) | K12: =IF(C12="","",IF(E12="Pessoal",IF(D12="Karina",C12,0),IF(N12=0,"",IF(G12=TRUE,C12/N12,0)))) | L12: =IF(C12="","",IF(E12="Pessoal",IF(D12="Bruno",C12,0),IF(N12=0,"",IF(H12=TRUE,C12/N12,0)))) | M12: =IF(C12="","",IF(E12="Pessoal",IF(D12="Gabriele",C12,0),IF(N12=0,"",IF(I12=TRUE,C12/N12,0)))) | N12: =IF(C12="","",IF(E12="Pessoal",1,COUNTIF(F12:I12,TRUE)))
F13: FALSE | G13: FALSE | H13: FALSE | I13: FALSE | J13: =IF(C13="","",IF(E13="Pessoal",IF(D13="Eduardo",C13,0),IF(N13=0,"",IF(F13=TRUE,C13/N13,0)))) | K13: =IF(C13="","",IF(E13="Pessoal",IF(D13="Karina",C13,0),IF(N13=0,"",IF(G13=TRUE,C13/N13,0)))) | L13: =IF(C13="","",IF(E13="Pessoal",IF(D13="Bruno",C13,0),IF(N13=0,"",IF(H13=TRUE,C13/N13,0)))) | M13: =IF(C13="","",IF(E13="Pessoal",IF(D13="Gabriele",C13,0),IF(N13=0,"",IF(I13=TRUE,C13/N13,0)))) | N13: =IF(C13="","",IF(E13="Pessoal",1,COUNTIF(F13:I13,TRUE)))
F14: FALSE | G14: FALSE | H14: FALSE | I14: FALSE | J14: =IF(C14="","",IF(E14="Pessoal",IF(D14="Eduardo",C14,0),IF(N14=0,"",IF(F14=TRUE,C14/N14,0)))) | K14: =IF(C14="","",IF(E14="Pessoal",IF(D14="Karina",C14,0),IF(N14=0,"",IF(G14=TRUE,C14/N14,0)))) | L14: =IF(C14="","",IF(E14="Pessoal",IF(D14="Bruno",C14,0),IF(N14=0,"",IF(H14=TRUE,C14/N14,0)))) | M14: =IF(C14="","",IF(E14="Pessoal",IF(D14="Gabriele",C14,0),IF(N14=0,"",IF(I14=TRUE,C14/N14,0)))) | N14: =IF(C14="","",IF(E14="Pessoal",1,COUNTIF(F14:I14,TRUE)))
F15: FALSE | G15: FALSE | H15: FALSE | I15: FALSE | J15: =IF(C15="","",IF(E15="Pessoal",IF(D15="Eduardo",C15,0),IF(N15=0,"",IF(F15=TRUE,C15/N15,0)))) | K15: =IF(C15="","",IF(E15="Pessoal",IF(D15="Karina",C15,0),IF(N15=0,"",IF(G15=TRUE,C15/N15,0)))) | L15: =IF(C15="","",IF(E15="Pessoal",IF(D15="Bruno",C15,0),IF(N15=0,"",IF(H15=TRUE,C15/N15,0)))) | M15: =IF(C15="","",IF(E15="Pessoal",IF(D15="Gabriele",C15,0),IF(N15=0,"",IF(I15=TRUE,C15/N15,0)))) | N15: =IF(C15="","",IF(E15="Pessoal",1,COUNTIF(F15:I15,TRUE)))
F16: FALSE | G16: FALSE | H16: FALSE | I16: FALSE | J16: =IF(C16="","",IF(E16="Pessoal",IF(D16="Eduardo",C16,0),IF(N16=0,"",IF(F16=TRUE,C16/N16,0)))) | K16: =IF(C16="","",IF(E16="Pessoal",IF(D16="Karina",C16,0),IF(N16=0,"",IF(G16=TRUE,C16/N16,0)))) | L16: =IF(C16="","",IF(E16="Pessoal",IF(D16="Bruno",C16,0),IF(N16=0,"",IF(H16=TRUE,C16/N16,0)))) | M16: =IF(C16="","",IF(E16="Pessoal",IF(D16="Gabriele",C16,0),IF(N16=0,"",IF(I16=TRUE,C16/N16,0)))) | N16: =IF(C16="","",IF(E16="Pessoal",1,COUNTIF(F16:I16,TRUE)))
... F121: FALSE | G121: FALSE | H121: FALSE | I121: FALSE | J121: =IF(C121="","",IF(E121="Pessoal",IF(D121="Eduardo",C121,0),IF(N121=0,"",IF(F121=TRUE,C121/N121,0)))) | K121: =IF(C121="","",IF(E121="Pessoal",IF(D121="Karina",C121,0),IF(N121=0,"",IF(G121=TRUE,C121/N121,0)))) | L121: =IF(C121="","",IF(E121="Pessoal",IF(D121="Bruno",C121,0),IF(N121=0,"",IF(H121=TRUE,C121/N121,0)))) | M121: =IF(C121="","",IF(E121="Pessoal",IF(D121="Gabriele",C121,0),IF(N121=0,"",IF(I121=TRUE,C121/N121,0)))) | N121: =IF(C121="","",IF(E121="Pessoal",1,COUNTIF(F121:I121,TRUE)))

Sheet Resumo
A1: Saldos entre vocês + quanto cada um está gastando na viagem
A3: Membro | B3: Total pagou (R$) | C3: Cota comum (R$) | D3: Gastos pessoais (R$) | E3: Custo da viagem (R$) | F3: Saldo Splitwise (R$) | G3: Situação
A4: Eduardo | B4: =SUMIF(Gastos!D:D,A4,Gastos!C:C) | C4: =SUMIF(Gastos!E:E,"Compartilhado",Gastos!J:J) | D4: =SUMIF(Gastos!E:E,"Pessoal",Gastos!J:J) | E4: =C4+D4 | F4: =B4-E4 | G4: =IF(F4>0.009,"A receber",IF(F4<-0.009,"A pagar","Quitado"))
A5: Karina | B5: =SUMIF(Gastos!D:D,A5,Gastos!C:C) | C5: =SUMIF(Gastos!E:E,"Compartilhado",Gastos!K:K) | D5: =SUMIF(Gastos!E:E,"Pessoal",Gastos!K:K) | E5: =C5+D5 | F5: =B5-E5 | G5: =IF(F5>0.009,"A receber",IF(F5<-0.009,"A pagar","Quitado"))
A6: Bruno | B6: =SUMIF(Gastos!D:D,A6,Gastos!C:C) | C6: =SUMIF(Gastos!E:E,"Compartilhado",Gastos!L:L) | D6: =SUMIF(Gastos!E:E,"Pessoal",Gastos!L:L) | E6: =C6+D6 | F6: =B6-E6 | G6: =IF(F6>0.009,"A receber",IF(F6<-0.009,"A pagar","Quitado"))
A7: Gabriele | B7: =SUMIF(Gastos!D:D,A7,Gastos!C:C) | C7: =SUMIF(Gastos!E:E,"Compartilhado",Gastos!M:M) | D7: =SUMIF(Gastos!E:E,"Pessoal",Gastos!M:M) | E7: =C7+D7 | F7: =B7-E7 | G7: =IF(F7>0.009,"A receber",IF(F7<-0.009,"A pagar","Quitado"))
A9: Totais do grupo
A10: Soma dos saldos (deve ser ~0): | B10: =SUM(F4:F7)
A11: Soma dos custos da viagem (4 pessoas): | B11: =SUM(E4:E7)
A12: Total lançado na aba Gastos: | B12: =SUM(Gastos!C:C)
A14: Filtro rápido na aba Gastos
A15: Use o filtro da coluna Tipo = Pessoal ou Compartilhado. Ou filtre Quem pagou = seu nome para ver só o que você lançou/pagou.
A16: Coluna Custo da viagem = o que interessa para 'quanto estou gastando' (sua parte + seus pessoais).

Sheet Acertos
A1: Acertos entre o grupo (só saldo compartilhado na prática)
A3: Os gastos pessoais não geram dívida. Acertes Pix/Zelle com base no Saldo Splitwise da aba Resumo. Registre abaixo quando transferir.
A5: Membro | B5: Saldo (R$) | C5: Situação
A6: =Resumo!A4 | B6: =Resumo!F4 | C6: =Resumo!G4
A7: =Resumo!A5 | B7: =Resumo!F5 | C7: =Resumo!G5
A8: =Resumo!A6 | B8: =Resumo!F6 | C8: =Resumo!G6
A9: =Resumo!A7 | B9: =Resumo!F7 | C9: =Resumo!G7
A11: Registro de transferências
A12: Data | B12: De (paga) | C12: Para (recebe) | D12: Valor (R$) | E12: Feito? | F12: Obs
E13: FALSE
E14: FALSE
E15: FALSE
E16: FALSE
E17: FALSE
E18: FALSE
E19: FALSE
E20: FALSE
E21: FALSE
E22: FALSE
E23: FALSE
E24: FALSE
... E32: FALSE

Sheet Categorias
A1: O que lançar e como classificar
A2: Tipo | B2: Categoria | C2: Exemplos | D2: Marcar quem?
A3: Compartilhado | B3: Casa / Carro / Seguro / Parking / Gasolina / Mercado | C3: Custos dos 4 adultos | D3: Os 4
A4: Compartilhado | B4: Comida / Uber / Outro comum | C4: Quando o grupo (ou parte) divide | D4: Quem participou
A5: Pessoal | B5: Ingresso | C5: Seu Disney/Universal/SeaWorld (se cada um compra o seu) | D5: Automático = quem pagou
A6: Pessoal | B6: Internet / Seguro viagem | C6: e-SIM, seguro individual | D6: Automático
A7: Pessoal | B7: Lembrancinha / Roupa / Farmácia | C7: Compras só suas | D7: Automático
A8: Pessoal | B8: Comida | C8: Almoço sozinho, snack só seu | D8: Automático
A9: Pessoal | B9: Outro pessoal | C9: Qualquer gasto só seu que queira somar no custo da viagem | D9: Automático
